{"py/object": "GameModels.PlayerData.PlayerData", "Id": "1483186265029090", "ListItem": [1], "ListScene": [{"py/object": "GameModels.SceneData.SceneData", "Id": 0, "ItemInScene": -1, "Description": "Description Scene 1", "ListConnection": [{"SceneId": 1, "py/object": "GameModels.SceneConnectionData.SceneConnectionData", "ListKeyWord": ["key word 1", "key word 2"]}], "SceneName": "Scene 1", "ListRequireItems": []}, {"py/object": "GameModels.SceneData.SceneData", "Id": 1, "ItemInScene": -1, "Description": "Description Scene 2", "ListConnection": [{"SceneId": 2, "py/object": "GameModels.SceneConnectionData.SceneConnectionData", "ListKeyWord": ["key word 1", "key word 2"]}, {"SceneId": 3, "py/object": "GameModels.SceneConnectionData.SceneConnectionData", "ListKeyWord": ["key word 3", "key word 4"]}], "SceneName": "Scene 2", "ListRequireItems": []}, {"py/object": "GameModels.SceneData.SceneData", "Id": 2, "ItemInScene": -1, "Description": "Description Scene 3", "ListConnection": [{"SceneId": 3, "py/object": "GameModels.SceneConnectionData.SceneConnectionData", "ListKeyWord": ["key word 1", "key word 2"]}], "SceneName": "Scene 3", "ListRequireItems": [1, 2]}, {"py/object": "GameModels.SceneData.SceneData", "Id": 3, "ItemInScene": 3, "Description": "Description Scene 4", "ListConnection": [], "SceneName": "Scene 4", "ListRequireItems": []}], "Name": "danh", "CurrentSceneId": 1}